nninteractive_slicer_server/__init__.py
nninteractive_slicer_server/main.py
nninteractive_slicer_server-0.3.0.dist-info/METADATA
nninteractive_slicer_server-0.3.0.dist-info/WHEEL
nninteractive_slicer_server-0.3.0.dist-info/entry_points.txt
nninteractive_slicer_server-0.3.0.dist-info/top_level.txt
nninteractive_slicer_server-0.3.0.dist-info/RECORD
