Metadata-Version: 2.4
Name: nninteractive-slicer-server
Version: 0.3.0
Summary: Server package for nnInteractive Slicer
Author-email: Coen de Vente <hello@coendevente.com>
License: Apache License (2.0)
Requires-Dist: nninteractive==1.0.1
Requires-Dist: fastapi==0.111.0
Requires-Dist: numpy==2.2.3
Requires-Dist: torch==2.8.0
Requires-Dist: Pillow==11.1.0
Requires-Dist: transformers==4.49.0
Requires-Dist: xxhash==3.5.0
